datalib_ha/__init__.py
datalib_ha/advanced_analysis.py
datalib_ha/data_manipulation.py
datalib_ha/statistics.py
datalib_ha/visualization.py
datalib_ha-1.0.0.dist-info/LICENSE
datalib_ha-1.0.0.dist-info/METADATA
datalib_ha-1.0.0.dist-info/WHEEL
datalib_ha-1.0.0.dist-info/top_level.txt
datalib_ha-1.0.0.dist-info/RECORD
