Metadata-Version: 2.1
Name: datalib-ha
Version: 1.0.0
Summary: A comprehensive data analysis library for Python
Home-page: https://github.com/ahmedhamila/Datalib
Author: Ahmed Hamila
Author-email: csahmed17@gmail.com
Project-URL: Documentation, https://datalib-ha.readthedocs.io
Project-URL: Source Code, https://github.com/ahmedhamila/datalib
Keywords: data-analysis statistics machine-learning
Classifier: Development Status :: 3 - Alpha
Classifier: Intended Audience :: Developers
Classifier: Intended Audience :: Science/Research
Classifier: License :: OSI Approved :: MIT License
Classifier: Programming Language :: Python :: 3.8
Classifier: Programming Language :: Python :: 3.9
Classifier: Programming Language :: Python :: 3.10
Classifier: Topic :: Scientific/Engineering :: Information Analysis
Requires-Python: >=3.8
License-File: LICENSE
Requires-Dist: pandas>=1.3.0
Requires-Dist: numpy>=1.21.0
Requires-Dist: matplotlib>=3.4.0
Requires-Dist: seaborn>=0.11.0
Requires-Dist: scikit-learn>=0.24.0
Requires-Dist: scipy>=1.7.0
Provides-Extra: dev
Requires-Dist: pytest; extra == "dev"
Requires-Dist: sphinx; extra == "dev"
